mkprop/CFMKprop.py
mkprop/KS.py
mkprop/Krylovprop.py
mkprop/KrylovpropSAI.py
mkprop/__init__.py
mkprop/smallexpimv.py
mkprop-0.0.4.dist-info/METADATA
mkprop-0.0.4.dist-info/WHEEL
mkprop-0.0.4.dist-info/licenses/LICENSE
mkprop-0.0.4.dist-info/RECORD
