Metadata-Version: 2.3
Name: mkprop
Version: 0.0.4
Summary: A python package for Krylov and Magnus-Krylov based time propagation.
Project-URL: Homepage, https://github.com/newbisi/mkprop
Project-URL: Issues, https://github.com/newbisi/mkprop/issues
Author-email: Tobias Jawecki <tobias.jawecki@gmail.com>
License-File: LICENSE
Keywords: Krylov method,Magnus integrator,time propagation
Classifier: License :: OSI Approved :: BSD License
Classifier: Operating System :: OS Independent
Classifier: Programming Language :: Python :: 3
Requires-Python: >=3.7
Requires-Dist: numpy
Requires-Dist: scipy
Requires-Dist: sympy
